readonce.py
readonce-1.1.3.dist-info/LICENSE
readonce-1.1.3.dist-info/WHEEL
readonce-1.1.3.dist-info/METADATA
readonce-1.1.3.dist-info/RECORD
