Metadata-Version: 2.1
Name: readonce
Version: 1.1.3
Summary: Read-Once Object implementation in Python - Inspired by Secure by Design book.
Author-email: Shako Rzayev <rzayev.sehriyar@gmail.com>
Requires-Python: >=3.10
Classifier: License :: OSI Approved :: MIT License
Requires-Dist: icontract >=2.6.2
Requires-Dist: cryptography >=40.0.2
Requires-Dist: black >=22.3.0 ; extra == "dev"
Requires-Dist: pylint >=2.12.2 ; extra == "dev"
Requires-Dist: isort >=5.9.3 ; extra == "dev"
Requires-Dist: autoflake >=1.4 ; extra == "dev"
Requires-Dist: flake8 >=4.0.1 ; extra == "dev"
Requires-Dist: pre-commit >=2.17.0 ; extra == "dev"
Requires-Dist: pytype >=2022.1.31 ; extra == "dev"
Requires-Dist: pydantic >=1.10.2 ; extra == "dev"
Requires-Dist: pytest >=7.3.1 ; extra == "test"
Requires-Dist: pytest-cov >= 3.0.0 ; extra == "test"
Provides-Extra: dev
Provides-Extra: test
